balsam/__init__.py
balsam/manage.py
balsam/core/GridFtp.py
balsam/core/__init__.py
balsam/core/admin.py
balsam/core/api_views.py
balsam/core/apps.py
balsam/core/forms.py
balsam/core/models.py
balsam/core/transfer.py
balsam/core/transitions.py
balsam/core/urls.py
balsam/core/views.py
balsam/django_config/__init__.py
balsam/django_config/db_index.py
balsam/django_config/default_settings.json
balsam/django_config/serverinfo.py
balsam/django_config/settings.py
balsam/django_config/theta_policy.ini
balsam/django_config/urls.py
balsam/django_config/views.py
balsam/django_config/wsgi.py
balsam/django_config/job-templates/bebop.slurm.tmpl
balsam/django_config/job-templates/cooley.cobaltscheduler.tmpl
balsam/django_config/job-templates/theta.cobaltscheduler.tmpl
balsam/django_config/job-templates/thetagpu.cobaltscheduler.tmpl
balsam/launcher/__init__.py
balsam/launcher/dag.py
balsam/launcher/futures.py
balsam/launcher/launcher.py
balsam/launcher/mpi_commands.py
balsam/launcher/mpi_ensemble2.py
balsam/launcher/multi_queue_fallback.py
balsam/launcher/serial_mode_timed.py
balsam/launcher/util.py
balsam/launcher/worker.py
balsam/scripts/__init__.py
balsam/scripts/cli.py
balsam/scripts/cli_commands.py
balsam/scripts/infolock.py
balsam/scripts/init.py
balsam/scripts/ls_commands.py
balsam/scripts/postgres_control.py
balsam/service/__init__.py
balsam/service/jobpacker.py
balsam/service/queues.py
balsam/service/service.py
balsam/service/pack/__init__.py
balsam/service/pack/boxpack.py
balsam/service/schedulers/CobaltScheduler.py
balsam/service/schedulers/JobEnvironment.py
balsam/service/schedulers/JobTemplate.py
balsam/service/schedulers/Scheduler.py
balsam/service/schedulers/SlurmScheduler.py
balsam/service/schedulers/__init__.py
balsam/service/schedulers/exceptions.py
balsam_flow-0.5.0.data/scripts/balsamactivate
balsam_flow-0.5.0.data/scripts/balsamdeactivate
balsam_flow-0.5.0.data/scripts/bcd
tests/benchmarks/__init__.py
tests/benchmarks/bench_insertion.py
balsam_flow-0.5.0.dist-info/LICENSE.md
balsam_flow-0.5.0.dist-info/METADATA
balsam_flow-0.5.0.dist-info/WHEEL
balsam_flow-0.5.0.dist-info/entry_points.txt
balsam_flow-0.5.0.dist-info/top_level.txt
balsam_flow-0.5.0.dist-info/RECORD
