Metadata-Version: 2.1
Name: balsam-flow
Version: 0.5.0
Summary: HPC Workflows & Edge Service
Home-page: https://balsam.readthedocs.io
Author: Misha Salim, Thomas Uram, Taylor Childers
Author-email: msalim@anl.gov
License: BSD 3-Clause License
Project-URL: Source, https://github.com/balsam-alcf/balsam
Project-URL: Documentation, https://balsam.readthedocs.io
Keywords: workflows,hpc,scientific,workflow
Platform: UNKNOWN
Classifier: Programming Language :: Python :: 3.6
Classifier: Programming Language :: Python :: 3.7
Classifier: Framework :: Django
Classifier: Development Status :: 5 - Production/Stable
Classifier: License :: OSI Approved :: BSD License
Classifier: Intended Audience :: Science/Research
Classifier: Topic :: Scientific/Engineering
Requires-Python: >=3.6
License-File: LICENSE.md
Requires-Dist: django (>=2.1.1)
Requires-Dist: django-widget-tweaks
Requires-Dist: python-dateutil
Requires-Dist: jinja2
Requires-Dist: psycopg2-binary
Requires-Dist: pyzmq
Requires-Dist: multiprocessing-logging
Requires-Dist: sphinx
Requires-Dist: sphinx-rtd-theme
Requires-Dist: setproctitle
Requires-Dist: numpy
Requires-Dist: psutil
Provides-Extra: docs
Requires-Dist: IPython ; extra == 'docs'
Requires-Dist: mkdocs ; extra == 'docs'
Requires-Dist: mkdocs-jupyter ; extra == 'docs'
Requires-Dist: mkdocs-material ; extra == 'docs'
